{
  "gitSyncId": "66bb01612693f95ee1a1358d_bd1c8370-f536-4ec5-8267-3924167f5e59",
  "id": "Page1_JSObject1.sel3_optList",
  "pluginId": "js-plugin",
  "pluginType": "JS",
  "unpublishedAction": {
    "actionConfiguration": {
      "encodeParamsToggle": true,
      "jsArguments": [],
      "paginationType": "NONE",
      "timeoutInMillisecond": 10000
    },
    "collectionId": "Page1_JSObject1",
    "confirmBeforeExecute": false,
    "datasource": {
      "isAutoGenerated": false,
      "name": "UNUSED_DATASOURCE",
      "pluginId": "js-plugin"
    },
    "dynamicBindingPathList": [
      {
        "key": "body"
      }
    ],
    "executeOnLoad": false,
    "fullyQualifiedName": "JSObject1.sel3_optList",
    "name": "sel3_optList",
    "pageId": "Page1",
    "userSetOnLoad": false
  }
}